{
    "entities": [
      {
        "tag": "player",
        "staticObject": false,
        "components": {
          "Transform": { "position": [100, 100, 0] },
          "Animator": [
            {
              "name": "default",
              "speed": 6,
              "texture": "assets/graphics/ennemy/red_ship.png",
              "frameCount": 8,
              "frameSize": [32, 32],
              "scale": [2, 2],
              "rotation": 0,
              "loop": true
            },
            {
              "name": "running",
              "speed": 10,
              "texture": "assets/graphics/player/charge.png",
              "frameCount": 8,
              "frameSize": [32, 32],
              "scale": [2, 2],
              "rotation": -90,
              "loop": false
            }
          ],
          "CppScripts": [
            "HelloWorld",
            "ChangeAnim",
            "MovePlayer"
          ]
        }
      },
      {
        "tag": "entity2",
        "staticObject": false,
        "components": {
          "Transform": { "position": [200, 100, 0] },
          "Sprite": { "texture": "assets/graphics/player.png" },
          "CppScripts": [
            "HelloWorld"
          ]
        }
      }
    ]
  }
  